sfisop/datamodels/__init__.py
sfisop/datamodels/tsdatamodel/__init__.py
sfisop/datamodels/tsdatamodel/metadata.py
sfisop/datamodels/tsdatamodel/timeseriesdata.py
sfisop/datamodels/tsdatamodel/tsdata_utils.py
sfisop_datamodels-1.0.1.dist-info/LICENSE
sfisop_datamodels-1.0.1.dist-info/METADATA
sfisop_datamodels-1.0.1.dist-info/WHEEL
sfisop_datamodels-1.0.1.dist-info/RECORD
