Metadata-Version: 2.1
Name: sfisop-datamodels
Version: 1.0.1
Summary: Basic time series data models for the Smart Ocean platform
Author: Smart Ocean WP3
Requires-Python: >=3.9,<4.0.0
Classifier: Programming Language :: Python :: 3
Classifier: Programming Language :: Python :: 3.9
Classifier: Programming Language :: Python :: 3.10
Classifier: Programming Language :: Python :: 3.11
Classifier: Programming Language :: Python :: 3.12
Classifier: Programming Language :: Python :: 3.13
Requires-Dist: pydantic (>=2.0,<3.0.0)
Requires-Dist: typing-extensions (>=4.6.3)
